deeprhythm/__init__.py
deeprhythm/batch_infer.py
deeprhythm/infer.py
deeprhythm/utils.py
deeprhythm/audio_proc/bandfilter.py
deeprhythm/audio_proc/hcqm.py
deeprhythm/audio_proc/onset.py
deeprhythm/dataset/clip_dataset.py
deeprhythm/dataset/intake.py
deeprhythm/dataset/song_dataset.py
deeprhythm/dataset/utils.py
deeprhythm/model/frame_cnn.py
deeprhythm/model/infer.py
deeprhythm/model/predictor.py
deeprhythm/model/train.py
deeprhythm-0.0.13.dist-info/METADATA
deeprhythm-0.0.13.dist-info/WHEEL
deeprhythm-0.0.13.dist-info/licenses/LICENSE
deeprhythm-0.0.13.dist-info/RECORD
