Metadata-Version: 2.3
Name: deeprhythm
Version: 0.0.13
Summary: A fast, accurate Tempo Predictor
Project-URL: Homepage, https://github.com/bleugreen/deeprhythm
Project-URL: Issues, https://github.com/bleugreen/deeprhythm/issues
Author-email: bleugreen <bleugreendesign@gmail.com>
Classifier: License :: OSI Approved :: GNU Affero General Public License v3
Classifier: Operating System :: OS Independent
Classifier: Programming Language :: Python :: 3
Requires-Python: >=3.8
Requires-Dist: librosa
Requires-Dist: nnaudio==0.3.3
Requires-Dist: numpy
Requires-Dist: torch
Requires-Dist: torchaudio
